LocUCT/__init__.py
LocUCT/annotation.py
LocUCT/geocoding.py
LocUCT/transformation.py
LocUCT-1.0.dist-info/METADATA
LocUCT-1.0.dist-info/WHEEL
LocUCT-1.0.dist-info/entry_points.txt
LocUCT-1.0.dist-info/top_level.txt
LocUCT-1.0.dist-info/RECORD
